tu_sphinx_theme.py
tu_sphinx_theme/__init__.py
tu_sphinx_theme/breadcrumbs.html
tu_sphinx_theme/fonts.html
tu_sphinx_theme/footer.html
tu_sphinx_theme/layout.html
tu_sphinx_theme/mathjax_config.html
tu_sphinx_theme/search.html
tu_sphinx_theme/searchbox.html
tu_sphinx_theme/theme.conf
tu_sphinx_theme/theme_variables.jinja
tu_sphinx_theme/versions.html
tu_sphinx_theme/static/css/theme.css
tu_sphinx_theme/static/fonts/FreightSans/freight-sans-bold-italic.woff
tu_sphinx_theme/static/fonts/FreightSans/freight-sans-bold-italic.woff2
tu_sphinx_theme/static/fonts/FreightSans/freight-sans-bold.woff
tu_sphinx_theme/static/fonts/FreightSans/freight-sans-bold.woff2
tu_sphinx_theme/static/fonts/FreightSans/freight-sans-book-italic.woff
tu_sphinx_theme/static/fonts/FreightSans/freight-sans-book-italic.woff2
tu_sphinx_theme/static/fonts/FreightSans/freight-sans-book.woff
tu_sphinx_theme/static/fonts/FreightSans/freight-sans-book.woff2
tu_sphinx_theme/static/fonts/FreightSans/freight-sans-light-italic.woff
tu_sphinx_theme/static/fonts/FreightSans/freight-sans-light-italic.woff2
tu_sphinx_theme/static/fonts/FreightSans/freight-sans-light.woff
tu_sphinx_theme/static/fonts/FreightSans/freight-sans-light.woff2
tu_sphinx_theme/static/fonts/FreightSans/freight-sans-medium-italic.woff
tu_sphinx_theme/static/fonts/FreightSans/freight-sans-medium-italic.woff2
tu_sphinx_theme/static/fonts/FreightSans/freight-sans-medium.woff
tu_sphinx_theme/static/fonts/FreightSans/freight-sans-medium.woff2
tu_sphinx_theme/static/fonts/IBMPlexMono/IBMPlexMono-Light.woff
tu_sphinx_theme/static/fonts/IBMPlexMono/IBMPlexMono-Light.woff2
tu_sphinx_theme/static/fonts/IBMPlexMono/IBMPlexMono-Medium.woff
tu_sphinx_theme/static/fonts/IBMPlexMono/IBMPlexMono-Medium.woff2
tu_sphinx_theme/static/fonts/IBMPlexMono/IBMPlexMono-Regular.woff
tu_sphinx_theme/static/fonts/IBMPlexMono/IBMPlexMono-Regular.woff2
tu_sphinx_theme/static/fonts/IBMPlexMono/IBMPlexMono-SemiBold.woff
tu_sphinx_theme-0.1.1.dist-info/LICENSE
tu_sphinx_theme-0.1.1.dist-info/METADATA
tu_sphinx_theme-0.1.1.dist-info/WHEEL
tu_sphinx_theme-0.1.1.dist-info/entry_points.txt
tu_sphinx_theme-0.1.1.dist-info/top_level.txt
tu_sphinx_theme-0.1.1.dist-info/RECORD
