Metadata-Version: 2.1
Name: tu_sphinx_theme
Version: 0.1.1
Summary: TorchUncertainty Sphinx Theme
Home-page: https://github.com/torch-uncertainty/tu_sphinx_theme
Author: TorchUncertainty Contributors
Author-email: olivier.laurent@ensta-paris.fr
License: MIT License
Classifier: Development Status :: 5 - Production/Stable
Classifier: Environment :: Web Environment
Classifier: Intended Audience :: Developers
Classifier: Intended Audience :: System Administrators
Classifier: License :: OSI Approved :: MIT License
Classifier: Operating System :: OS Independent
Classifier: Programming Language :: Python
Classifier: Topic :: Internet
Classifier: Topic :: Software Development :: Documentation
License-File: LICENSE
Requires-Dist: sphinx
